agentvec/__init__.py
agentvec/agentvec.cpython-38-x86_64-linux-gnu.so
agentvec-0.2.0.dist-info/METADATA
agentvec-0.2.0.dist-info/WHEEL
agentvec-0.2.0.dist-info/RECORD
