Metadata-Version: 2.4
Name: agentvec
Version: 0.2.0
Classifier: Development Status :: 4 - Beta
Classifier: Intended Audience :: Developers
Classifier: License :: OSI Approved :: MIT License
Classifier: License :: OSI Approved :: Apache Software License
Classifier: Programming Language :: Python :: 3
Classifier: Programming Language :: Python :: 3.8
Classifier: Programming Language :: Python :: 3.9
Classifier: Programming Language :: Python :: 3.10
Classifier: Programming Language :: Python :: 3.11
Classifier: Programming Language :: Python :: 3.12
Classifier: Programming Language :: Python :: 3.13
Classifier: Programming Language :: Rust
Classifier: Topic :: Database
Classifier: Topic :: Scientific/Engineering :: Artificial Intelligence
Summary: A lightweight, serverless vector database for AI agent memory
Keywords: vector,database,embedding,ai,agent,memory
License: MIT OR Apache-2.0
Requires-Python: >=3.8
Project-URL: Documentation, https://github.com/Akuming/agentvec#readme
Project-URL: Issues, https://github.com/Akuming/agentvec/issues
Project-URL: Repository, https://github.com/Akuming/agentvec
